Workbook

Sheet Group Members
C2: S.No | D2: ID | E2: Name | F2: Company Assigned
C3: 1 | D3: 2022A3PS1224P | E3: Vishwam Aggarwal | F3: Anupam Rasayan Ltd.
C4: 2 | D4: 2022A1PS1356P | E4: Anand Kashyap
C5: 3 | D5: 2022A1PS1075P | E5: Ayush Saharia
C6: 4 | D6: 2022A1PS0883P | E6: Samagra Kumar Tiwari

Sheet CAPM (Monthly) (Part-1)
A1: Data for Anupam Rasayan | D1: Returns | F1: DATA for NIFTY 50 | H1: Return | O1: Market Returns for NIFTY 50 | S1: Average Market Return | T1: 91 day T-bill | X1: Market Risk Premium | AA1: Dividend Data | AM1: Liability Breakdown (Rs in Millions) | AP1: Interest Expense (Rs in Millions) | AS1: Bond Yield Plus Risk Premium Approach (Cost of Equity=Bond Yield+ Equity Risk Premium) | BE1: The Fama-French Three-Factor Model Formula:
A2: Date | B2: Close | F2: Date | G2: Close | J2: Covariance | K2: Variance | L2: Beta | O2: 2024 | T2: (Risk free Rate) | X2: (Rm-RFR) | AA2: Announcement Date | AB2: Ex-Dividend Date | AC2: Dividend (Rs) | AE2: Years | AF2: Sum of Dividend (Rs) | AH2: We can clearly see that dividend given out by the company is showing a clear negative trend hence dividend discount model of any kind cannot be used. | AM2: Total Liability | AN2: 16143.58 | AP2: Interest Expense | AQ2: 792.69 | BM2: All values are in % | BQ2: MF (market Factor/ Market Return): | BR2: RF (Risk Free Rate):
A3: 44256 | B3: 489.15 | F3: 44256 | G3: 14690.7 | J3: =_xlfn.COVARIANCE.P(D4:D47,H4:H47) -> 0.0017156319 | K3: =_xlfn.VAR.P(H4:H47) -> 0.0013534673 | L3: =J3/K3 -> 1.2675828 | O3: 2023 | P3: 19.42 | S3: 15.609167 | T3: 6.5 | U3: Cost of Equity (CAPM) = | V3: =V4*100 -> 18.046623 | W3: % | X3: =(S4-T4) -> 0.091091667 | AA3: 45433 | AB3: 45552 | AC3: 0.75 | AE3: 2021 | AF3: 3 | AM3: Current Liability | AN3: 12663.46 | AP3: Other Borrowing Cost | AQ3: 44.48 | BK3: Date:- | BL3: Excess Return on Asset | BM3: SMB | BN3: HML | BO3: Rm-Rf | BP3: WML
A4: 44287 | B4: 624.25 | D4: =(B4-B3)/B3 -> 0.2761934 | F4: 44287 | G4: 14631.1 | H4: =(G4-G3)/G3 -> -0.0040569884 | O4: 2022 | P4: 4.32 | S4: =S3/100 -> 0.15609167 | T4: =T3/100 -> 0.065 | V4: =T4+L3*(S4-T4) -> 0.18046623 | X4: =X3*100 -> 9.1091667 | AA4: 45237 | AB4: 45250 | AC4: 0.5 | AE4: 2022 | AF4: 2.2 | AM4: Long term Liability | AN4: =AN2-AN3 -> 3480.12 | BK4: 2021-04 | BL4: =(D4*100)-BR4 -> 27.349334 | BM4: 0.6491973 | BN4: 10.539244 | BO4: =BQ4-BR4 -> 1.195097 | BP4: 5.8040857 | BQ4: 1.4651031 | BR4: 0.27000609 | BU4: SUMMARY OUTPUT
A5: 44317 | B5: 754.25 | D5: =(B5-B4)/B4 -> 0.2082499 | F5: 44317 | G5: 15582.8 | H5: =(G5-G4)/G4 -> 0.065046374 | O5: 2021 | P5: 24.12 | AA5: 45049 | AB5: 45061 | AC5: 1.5 | AE5: 2023 | AF5: 2.6 | AP5: Estimated Yield of Long term Bond (%) | AQ5: =AQ2/AN4 -> 0.22777663 | AS5: Cost of Equity= | AV5: =AQ6+X4 -> 31.88683 | AX5: E: Market value of Equity | BA5: =AN6 -> 27365.51 | BF5: Last month | BG5: Last 3 months | BH5: Year to date | BI5: Since 01-Jan-1994 | BK5: 2021-05 | BL5: =(D5*100)-BR5 -> 20.54416 | BM5: 5.4578512 | BN5: 2.2742174 | BO5: =BQ5-BR5 -> 7.1317207 | BP5: 0.33800694 | BQ5: 7.4125512 | BR5: 0.28083045
A6: 44348 | B6: 760 | D6: =(B6-B5)/B5 -> 0.007623467 | F6: 44348 | G6: 15721.5 | H6: =(G6-G5)/G5 -> 0.0089008394 | O6: 2020 | P6: 14.9 | AA6: 44953 | AB6: 44965 | AC6: 0.6 | AE6: 2024 | AF6: 0.75 | AM6: Total Equity | AN6: 27365.51 | AQ6: =AQ5*100 -> 22.777663 | AR6: % | AV6: =AV5/100 -> 0.3188683 | AX6: V: Debt+Equity (E+D) | BA6: =AN2+AN6 -> 43509.09 | BE6: Market premium % | BF6: 2.744155 | BG6: -33.77817 | BH6: -33.77817 | BI6: 4.143206 | BK6: 2021-06 | BL6: =(D6*100)-BR6 -> 0.4845074 | BM6: 7.7699152 | BN6: 4.7403864 | BO6: =BQ6-BR6 -> 2.8089051 | BP6: -1.7305545 | BQ6: 3.0867444 | BR6: 0.2778393 | BU6: Regression Statistics
A7: 44378 | B7: 726.4 | D7: =(B7-B6)/B6 -> -0.044210526 | F7: 44378 | G7: 15763.05 | H7: =(G7-G6)/G6 -> 0.0026428776 | O7: 2019 | P7: 12.02 | AA7: 44693 | AB7: 44806 | AC7: 1 | AE7: Grand Total | AF7: 8.55 | AX7: r_e: Cost of Equity (CAPM) | BA7: =V4 -> 0.18046623 | BE7: SMB % | BF7: -25.923507 | BG7: -16.91952 | BH7: -16.91952 | BI7: -4.543637 | BK7: 2021-07 | BL7: =(D7*100)-BR7 -> -4.6986103 | BM7: 5.052861 | BN7: 6.7052357 | BO7: =BQ7-BR7 -> 1.4359835 | BP7: 3.4943011 | BQ7: 1.7135412 | BR7: 0.27755769 | BU7: Multiple R | BV7: 0.57079885
A8: 44409 | B8: 761.6 | D8: =(B8-B7)/B7 -> 0.04845815 | F8: 44409 | G8: 17132.2 | H8: =(G8-G7)/G7 -> 0.086858191 | O8: 2018 | P8: 3.15 | AA8: 44767 | AB8: 44776 | AC8: 0.4 | AX8: r_e: Cost of Equity (Bond Yield approach) | BA8: =AV6 -> 0.3188683 | BE8: HML % | BF8: 14.716229 | BG8: 21.71195 | BH8: 21.71195 | BI8: 6.552079 | BK8: 2021-08 | BL8: =(D8*100)-BR8 -> 4.5560008 | BM8: -8.3949225 | BN8: -6.9714962 | BO8: =BQ8-BR8 -> 5.4379455 | BP8: 3.9728501 | BQ8: 5.7277597 | BR8: 0.28981422 | BU8: R Square | BV8: 0.32581133
A9: 44440 | B9: 803.95 | D9: =(B9-B8)/B8 -> 0.055606618 | F9: 44440 | G9: 17618.15 | H9: =(G9-G8)/G8 -> 0.028364717 | O9: 2017 | P9: 28.65 | AA9: 44503 | AB9: 44517 | AC9: 0.5 | BE9: WML % | BF9: 15.962009 | BG9: -14.62498 | BH9: -14.62498 | BI9: 10.996853 | BK9: 2021-09 | BL9: =(D9*100)-BR9 -> 5.292827 | BM9: -1.4727894 | BN9: 10.66231 | BO9: =BQ9-BR9 -> 3.8451046 | BP9: -2.2344153 | BQ9: 4.1129394 | BR9: 0.26783476 | BU9: Adjusted R Square | BV9: 0.18387688
A10: 44470 | B10: 802.85 | D10: =(B10-B9)/B9 -> -0.0013682443 | F10: 44470 | G10: 17671.65 | H10: =(G10-G9)/G9 -> 0.0030366412 | O10: 2016 | P10: 3.01 | AA10: 44361 | AB10: 44454 | AC10: 0.5 | AX10: D: Value of Debt | BA10: =AN2 -> 16143.58 | BK10: 2021-10 | BL10: =(D10*100)-BR10 -> -0.40652078 | BM10: 1.7123054 | BN10: 0.60131906 | BO10: =BQ10-BR10 -> -1.3747763 | BP10: 6.6838387 | BQ10: -1.1050799 | BR10: 0.26969635 | BU10: Standard Error | BV10: 12.892225
A11: 44501 | B11: 789.15 | D11: =(B11-B10)/B10 -> -0.017064209 | F11: 44501 | G11: 16983.2 | H11: =(G11-G10)/G10 -> -0.038957879 | O11: 2015 | P11: -4.06 | AA11: 44767 | AB11: 44776 | AC11: 0.4 | AX11: r_d: Cost of Debt | BA11: =AQ5 -> 0.22777663 | BE11: Start Month | BF11: 34243 | BK11: 2021-11 | BL11: =(D11*100)-BR11 -> -2.0136881 | BM11: 1.9695719 | BN11: -1.6546471 | BO11: =BQ11-BR11 -> -1.3296586 | BP11: 4.569058 | BQ11: -1.0223913 | BR11: 0.30726727 | BU11: Observations | BV11: 24
A12: 44531 | B12: 990.75 | D12: =(B12-B11)/B11 -> 0.25546474 | F12: 44531 | G12: 17354.05 | H12: =(G12-G11)/G11 -> 0.021836285 | O12: 2014 | P12: 31.39 | AA12: 44503 | AB12: 44517 | AC12: 0.5 | AX12: Tax Rate | BA12: 0.25 | BE12: End Month | BF12: 44986 | BK12: 2021-12 | BL12: =(D12*100)-BR12 -> 25.248507 | BM12: 5.9782451 | BN12: 1.2897451 | BO12: =BQ12-BR12 -> 3.5273656 | BP12: 3.5805724 | BQ12: 3.8253328 | BR12: 0.29796728
A13: 44562 | B13: 963.5 | D13: =(B13-B12)/B12 -> -0.027504416 | F13: 44562 | G13: 17339.85 | H13: =(G13-G12)/G12 -> -0.0008182528 | O13: 2013 | P13: 6.76 | AA13: 44361 | AB13: 44454 | AC13: 0.5 | BB13: in Percentage (%) | BK13: 2022-01 | BL13: =(D13*100)-BR13 -> -3.0534749 | BM13: -0.2288274 | BN13: 10.931499 | BO13: =BQ13-BR13 -> -1.8761949 | BP13: -0.018796784 | BQ13: -1.5731616 | BR13: 0.30303333 | BU13: ANOVA
A14: 44593 | B14: 837.05 | D14: =(B14-B13)/B13 -> -0.13124027 | F14: 44593 | G14: 16793.9 | H14: =(G14-G13)/G13 -> -0.031485278 | O14: 2012 | P14: 27.7 | AA14: 44767 | AB14: 44776 | AC14: 0.4 | AX14: WACC (CAPM apporach) | BA14: =((BA5/BA6)*BA7)+((BA10/BA6)*BA11*(1-BA12)) -> 0.17689173 | BB14: =BA14*100 -> 17.689173 | BC14: % | BE14: Source:- https://web.iima.ac.in/~iffm/Indian-Fama-French-Momentum/index.php | BK14: 2022-02 | BL14: =(D14*100)-BR14 -> -13.409388 | BM14: -6.832612 | BN14: -1.8273542 | BO14: =BQ14-BR14 -> -4.710292 | BP14: -2.4552567 | BQ14: -4.4249312 | BR14: 0.28536076 | BV14: df | BW14: SS | BX14: MS | BY14: F | BZ14: Significance F
A15: 44621 | B15: 824.45 | D15: =(B15-B14)/B14 -> -0.015052864 | F15: 44621 | G15: 17464.75 | H15: =(G15-G14)/G14 -> 0.039946052 | O15: 2011 | P15: -24.62 | AA15: 44503 | AB15: 44517 | AC15: 0.5 | AX15: WACC (Bond Yield apporach) | BA15: =((BA5/BA6)*BA8)+((BA10/BA6)*BA11*(1-BA12)) -> 0.26394119 | BB15: =BA15*100 -> 26.394119 | BC15: % | BK15: 2022-03 | BL15: =(D15*100)-BR15 -> -1.8203812 | BM15: 2.110784 | BN15: 0.7905411 | BO15: =BQ15-BR15 -> 4.4190756 | BP15: 7.2255747 | BQ15: 4.7341704 | BR15: 0.31509482 | BU15: Regression | BV15: 4 | BW15: 1526.139 | BX15: 381.53474 | BY15: 2.2955056 | BZ15: 0.096760852
A16: 44652 | B16: 828.6 | D16: =(B16-B15)/B15 -> 0.0050336588 | F16: 44652 | G16: 17102.55 | H16: =(G16-G15)/G15 -> -0.020738917 | O16: 2010 | P16: 17.95 | AA16: 44361 | AB16: 44454 | AC16: 0.5 | BK16: 2022-04 | BL16: =(D16*100)-BR16 -> 0.19738443 | BM16: 2.1924603 | BN16: 4.4905873 | BO16: =BQ16-BR16 -> 1.0617866 | BP16: -2.9122357 | BQ16: 1.367768 | BR16: 0.30598145 | BU16: Residual | BV16: 19 | BW16: 3157.9798 | BX16: 166.20946
A17: 44682 | B17: 687.65 | D17: =(B17-B16)/B16 -> -0.1701062 | F17: 44682 | G17: 16584.55 | H17: =(G17-G16)/G16 -> -0.030287881 | O17: 2009 | P17: 75.76 | BK17: 2022-05 | BL17: =(D17*100)-BR17 -> -17.403469 | BM17: -3.4015396 | BN17: -2.2869047 | BO17: =BQ17-BR17 -> -6.9566241 | BP17: -6.0227346 | BQ17: -6.5637757 | BR17: 0.39284838 | BU17: Total | BV17: 23 | BW17: 4684.1188
A18: 44713 | B18: 610.1 | D18: =(B18-B17)/B17 -> -0.11277539 | F18: 44713 | G18: 15780.25 | H18: =(G18-G17)/G17 -> -0.048496944 | O18: 2008 | P18: -51.79 | BK18: 2022-06 | BL18: =(D18*100)-BR18 -> -11.680982 | BM18: 0.2137815 | BN18: -2.8098945 | BO18: =BQ18-BR18 -> -5.3456301 | BP18: 1.8592887 | BQ18: -4.942188 | BR18: 0.40344207
A19: 44743 | B19: 796.75 | D19: =(B19-B18)/B18 -> 0.30593345 | F19: 44743 | G19: 17158.25 | H19: =(G19-G18)/G18 -> 0.087324345 | O19: 2007 | P19: 54.77 | BK19: 2022-07 | BL19: =(D19*100)-BR19 -> 30.185226 | BM19: 2.2470931 | BN19: -3.3513363 | BO19: =BQ19-BR19 -> 7.8960624 | BP19: -2.8933446 | BQ19: 8.3041821 | BR19: 0.40811974 | BV19: Coefficients | BW19: Standard Error | BX19: t Stat | BY19: P-value | BZ19: Lower 95% | CA19: Upper 95% | CB19: Lower 95.0% | CC19: Upper 95.0%
A20: 44774 | B20: 777 | D20: =(B20-B19)/B19 -> -0.024788202 | F20: 44774 | G20: 17759.3 | H20: =(G20-G19)/G19 -> 0.035029796 | O20: 2006 | P20: 39.83 | BK20: 2022-08 | BL20: =(D20*100)-BR20 -> -2.956053 | BM20: 1.2287121 | BN20: 2.4731591 | BO20: =BQ20-BR20 -> 4.4127181 | BP20: 5.8556121 | BQ20: 4.8899509 | BR20: 0.47723275 | BU20: Intercept | BV20: 2.3165107 | BW20: 3.0085478 | BX20: 0.76997636 | BY20: 0.45078182 | BZ20: -3.9804523 | CA20: 8.6134736 | CB20: -3.9804523 | CC20: 8.6134736
A21: 44805 | B21: 751.15 | D21: =(B21-B20)/B20 -> -0.033268983 | F21: 44805 | G21: 17094.35 | H21: =(G21-G20)/G20 -> -0.037442354 | O21: 2005 | P21: 36.34 | BK21: 2022-09 | BL21: =(D21*100)-BR21 -> -3.8017741 | BM21: 3.2997202 | BN21: -2.0141931 | BO21: =BQ21-BR21 -> -4.0541134 | BP21: 1.4322461 | BQ21: -3.5792376 | BR21: 0.47487581 | BU21: SMB | BV21: 0.13085024 | BW21: 0.7802251 | BX21: 0.16770832 | BY21: 0.86858496 | BZ21: -1.5021797 | CA21: 1.7638801 | CB21: -1.5021797 | CC21: 1.7638801
A22: 44835 | B22: 759.95 | D22: =(B22-B21)/B21 -> 0.01171537 | F22: 44835 | G22: 18012.2 | H22: =(G22-G21)/G21 -> 0.053693179 | O22: 2004 | P22: 10.68 | BK22: 2022-10 | BL22: =(D22*100)-BR22 -> 0.65480546 | BM22: -2.5174924 | BN22: 3.2116556 | BO22: =BQ22-BR22 -> 1.3427251 | BP22: -0.11801266 | BQ22: 1.8594566 | BR22: 0.51673152 | BU22: HML | BV22: 0.02288942 | BW22: 0.61603879 | BX22: 0.037155809 | BY22: 0.97074839 | BZ22: -1.2664946 | CA22: 1.3122734 | CB22: -1.2664946 | CC22: 1.3122734
A23: 44866 | B23: 719.05 | D23: =(B23-B22)/B22 -> -0.05381933 | F23: 44866 | G23: 18758.35 | H23: =(G23-G22)/G22 -> 0.041424701 | O23: 2003 | P23: 71.9 | BK23: 2022-11 | BL23: =(D23*100)-BR23 -> -5.8969638 | BM23: -0.46622365 | BN23: 5.7887239 | BO23: =BQ23-BR23 -> 1.7868428 | BP23: -1.5132308 | BQ23: 2.3018736 | BR23: 0.51503079 | BU23: Rm-Rf | BV23: 1.8080718 | BW23: 0.67436026 | BX23: 2.681166 | BY23: 0.014777068 | BZ23: 0.39661958 | CA23: 3.2195241 | CB23: 0.39661958 | CC23: 3.2195241
A24: 44896 | B24: 679.45 | D24: =(B24-B23)/B23 -> -0.055072665 | F24: 44896 | G24: 18105.3 | H24: =(G24-G23)/G23 -> -0.03481383 | O24: 2002 | P24: 3.25 | BK24: 2022-12 | BL24: =(D24*100)-BR24 -> -6.0182976 | BM24: 1.6786937 | BN24: 3.1650308 | BO24: =BQ24-BR24 -> -4.4912733 | BP24: -0.085831971 | BQ24: -3.9802422 | BR24: 0.51103104 | BU24: WML | BV24: 0.12878169 | BW24: 0.793993 | BX24: 0.16219499 | BY24: 0.87286479 | BZ24: -1.5330648 | CA24: 1.7906281 | CB24: -1.5330648 | CC24: 1.7906281
A25: 44927 | B25: 593.6 | D25: =(B25-B24)/B24 -> -0.1263522 | F25: 44927 | G25: 17662.15 | H25: =(G25-G24)/G24 -> -0.024476258 | O25: 2001 | P25: -16.18 | BE25: Required Rate of Return according Fama-French Model = | BF25: =T3/12+BV23*X4+BV21*BI7+BV22*BI8+BV24*BI9+BV20 -> 20.299835 | BG25: % | BK25: 2023-01 | BL25: =(D25*100)-BR25 -> -13.179622 | BM25: 0.37775377 | BN25: 3.6494669 | BO25: =BQ25-BR25 -> -5.0937245 | BP25: -3.2653055 | BQ25: -4.5493222 | BR25: 0.54440229
A26: 44958 | B26: 645.15 | D26: =(B26-B25)/B25 -> 0.086842992 | F26: 44958 | G26: 17303.95 | H26: =(G26-G25)/G25 -> -0.020280657 | O26: 2000 | P26: -14.65 | BK26: 2023-02 | BL26: =(D26*100)-BR26 -> 8.187283 | BM26: -2.3195572 | BN26: 0.038092368 | BO26: =BQ26-BR26 -> -5.9589538 | BP26: -1.7739889 | BQ26: -5.4619376 | BR26: 0.49701615
A27: 44986 | B27: 865.35 | D27: =(B27-B26)/B26 -> 0.34131597 | F27: 44986 | G27: 17359.75 | H27: =(G27-G26)/G26 -> 0.0032246973 | O27: Source | BK27: 2023-03 | BL27: =(D27*100)-BR27 -> 33.566538 | BM27: -2.5146541 | BN27: 1.1720531 | BO27: =BQ27-BR27 -> -0.33502744 | BP27: 1.2648428 | BQ27: 0.23003149 | BR27: 0.56505892
A28: 45017 | B28: 1129.3 | D28: =(B28-B27)/B27 -> 0.30502109 | F28: 45017 | G28: 18065 | H28: =(G28-G27)/G27 -> 0.040625585 | O28: https://primeinvestor.in/nifty-50-returns/
A29: 45047 | B29: 1166 | D29: =(B29-B28)/B28 -> 0.032498008 | F29: 45047 | G29: 18534.4 | H29: =(G29-G28)/G28 -> 0.025983947 | BE29: Disclaimer:- The required Rate of return calculated from Fama French Theory may not be entirely accurate as we were unable to find the value unable to find the values of SMB,HML, and WML beyond March 2023.
A30: 45078 | B30: 1030 | D30: =(B30-B29)/B29 -> -0.11663808 | F30: 45078 | G30: 19189.05 | H30: =(G30-G29)/G29 -> 0.035320809
A31: 45108 | B31: 974.9 | D31: =(B31-B30)/B30 -> -0.053495146 | F31: 45108 | G31: 19753.8 | H31: =(G31-G30)/G30 -> 0.029430847
A32: 45139 | B32: 1004.95 | D32: =(B32-B31)/B31 -> 0.030823674 | F32: 45139 | G32: 19253.8 | H32: =(G32-G31)/G31 -> -0.025311586
A33: 45170 | B33: 884.85 | D33: =(B33-B32)/B32 -> -0.11950843 | F33: 45170 | G33: 19638.3 | H33: =(G33-G32)/G32 -> 0.019970084
A34: 45200 | B34: 883.55 | D34: =(B34-B33)/B33 -> -0.0014691756 | F34: 45200 | G34: 19079.6 | H34: =(G34-G33)/G33 -> -0.028449509
A35: 45231 | B35: 986.6 | D35: =(B35-B34)/B34 -> 0.11663177 | F35: 45231 | G35: 20133.15 | H35: =(G35-G34)/G34 -> 0.055218663 | BE35: HML = high-minus-low factor
A36: 45261 | B36: 1052.05 | D36: =(B36-B35)/B35 -> 0.066338942 | F36: 45261 | G36: 21731.4 | H36: =(G36-G35)/G35 -> 0.079384001 | BE36: SMB = the small-minus-big factor
A37: 45292 | B37: 949.3 | D37: =(B37-B36)/B36 -> -0.097666461 | F37: 45292 | G37: 21725.7 | H37: =(G37-G36)/G36 -> -0.00026229327 | BE37: WML = Winner Minus Loser (adds momentum dimension)
A38: 45323 | B38: 956.3 | D38: =(B38-B37)/B37 -> 0.0073738544 | F38: 45323 | G38: 21982.8 | H38: =(G38-G37)/G37 -> 0.011833911
A39: 45352 | B39: 870.45 | D39: =(B39-B38)/B38 -> -0.089773084 | F39: 45352 | G39: 22326.9 | H39: =(G39-G38)/G38 -> 0.015653147
A40: 45383 | B40: 832.55 | D40: =(B40-B39)/B39 -> -0.043540697 | F40: 45383 | G40: 22604.85 | H40: =(G40-G39)/G39 -> 0.012449108
A41: 45413 | B41: 762.65 | D41: =(B41-B40)/B40 -> -0.083958921 | F41: 45413 | G41: 22530.7 | H41: =(G41-G40)/G40 -> -0.0032802695
A42: 45444 | B42: 764.75 | D42: =(B42-B41)/B41 -> 0.0027535567 | F42: 45444 | G42: 24010.6 | H42: =(G42-G41)/G41 -> 0.065683712
A43: 45474 | B43: 783.95 | D43: =(B43-B42)/B42 -> 0.025106244 | F43: 45474 | G43: 24951.15 | H43: =(G43-G42)/G42 -> 0.039172282
A44: 45505 | B44: 778.8 | D44: =(B44-B43)/B43 -> -0.0065692965 | F44: 45505 | G44: 25235.9 | H44: =(G44-G43)/G43 -> 0.0114123
A45: 45536 | B45: 736.95 | D45: =(B45-B44)/B44 -> -0.053736518 | F45: 45536 | G45: 25810.85 | H45: =(G45-G44)/G44 -> 0.022783019
A46: 45566 | B46: 733.4 | D46: =(B46-B45)/B45 -> -0.0048171518 | F46: 45566 | G46: 24205.35 | H46: =(G46-G45)/G45 -> -0.062202523
A47: 45597 | B47: 723.3 | D47: =(B47-B46)/B46 -> -0.013771475 | F47: 45597 | G47: 23559.05 | H47: =(G47-G46)/G46 -> -0.026700709

Sheet CAPM (Weekly) (Part-1)
A1: Data for Anupam Rasayan | D1: Returns | F1: DATA for NIFTY 50 | H1: Return | O1: Merket Returns for NIFTY 50 | S1: Average Return | T1: 91 day T-bill | U1: Cost of Equity
A2: Date | B2: Close | F2: Date | G2: Close | J2: Covariance | K2: Variance | L2: Beta | O2: 2024 | T2: (Risk free Rate) | U2: (CAPM)
A3: 44279 | B3: 495.7 | F3: 44277 | G3: 14507.3 | J3: =_xlfn.COVARIANCE.P(D4:D195,H4:H195) -> 0.00020553315 | K3: =_xlfn.VAR.P(H4:H195) -> 0.00031883116 | L3: =J3/K3 -> 0.64464575 | O3: 2023 | P3: 19.42 | S3: 15.609167 | T3: 6.5 | U3: =U4*100 -> 12.372186
A4: 44285 | B4: 516.95 | D4: =(B4-B3)/B3 -> 0.042868671 | F4: 44285 | G4: 14867.35 | H4: =(G4-G3)/G3 -> 0.02481854 | O4: 2022 | P4: 4.32 | S4: =S3/100 -> 0.15609167 | T4: =T3/100 -> 0.065 | U4: =T4+L3*(S4-T4) -> 0.12372186
A5: 44291 | B5: 555.25 | D5: =(B5-B4)/B4 -> 0.074088403 | F5: 44291 | G5: 14834.85 | H5: =(G5-G4)/G4 -> -0.0021859982 | O5: 2021 | P5: 24.12
A6: 44298 | B6: 579.95 | D6: =(B6-B5)/B5 -> 0.044484466 | F6: 44298 | G6: 14617.85 | H6: =(G6-G5)/G5 -> -0.014627718 | O6: 2020 | P6: 14.9
A7: 44305 | B7: 590 | D7: =(B7-B6)/B6 -> 0.01732908 | F7: 44305 | G7: 14341.35 | H7: =(G7-G6)/G6 -> -0.01891523 | O7: 2019 | P7: 12.02
A8: 44312 | B8: 624.25 | D8: =(B8-B7)/B7 -> 0.058050847 | F8: 44312 | G8: 14631.1 | H8: =(G8-G7)/G7 -> 0.020203816 | O8: 2018 | P8: 3.15
A9: 44319 | B9: 721.1 | D9: =(B9-B8)/B8 -> 0.15514618 | F9: 44319 | G9: 14823.15 | H9: =(G9-G8)/G8 -> 0.013126149 | O9: 2017 | P9: 28.65
A10: 44326 | B10: 734.45 | D10: =(B10-B9)/B9 -> 0.018513382 | F10: 44326 | G10: 14677.8 | H10: =(G10-G9)/G9 -> -0.0098056081 | O10: 2016 | P10: 3.01
A11: 44333 | B11: 769.4 | D11: =(B11-B10)/B10 -> 0.047586629 | F11: 44333 | G11: 15175.3 | H11: =(G11-G10)/G10 -> 0.033894725 | O11: 2015 | P11: -4.06
A12: 44340 | B12: 761.5 | D12: =(B12-B11)/B11 -> -0.010267741 | F12: 44340 | G12: 15435.65 | H12: =(G12-G11)/G11 -> 0.017156168 | O12: 2014 | P12: 31.39
A13: 44347 | B13: 769.25 | D13: =(B13-B12)/B12 -> 0.010177282 | F13: 44347 | G13: 15670.25 | H13: =(G13-G12)/G12 -> 0.015198583 | O13: 2013 | P13: 6.76
A14: 44354 | B14: 777.65 | D14: =(B14-B13)/B13 -> 0.010919727 | F14: 44354 | G14: 15799.35 | H14: =(G14-G13)/G13 -> 0.0082385412 | O14: 2012 | P14: 27.7
A15: 44361 | B15: 733.2 | D15: =(B15-B14)/B14 -> -0.05715939 | F15: 44361 | G15: 15683.35 | H15: =(G15-G14)/G14 -> -0.0073420742 | O15: 2011 | P15: -24.62
A16: 44368 | B16: 745.25 | D16: =(B16-B15)/B15 -> 0.016434806 | F16: 44368 | G16: 15860.35 | H16: =(G16-G15)/G15 -> 0.011285854 | O16: 2010 | P16: 17.95
... A26: 44438 | B26: 754.7 | D26: =(B26-B25)/B25 -> 0.024155245 | F26: 44438 | G26: 17323.6 | H26: =(G26-G25)/G25 -> 0.037018413 | O26: 2000 | P26: -14.65
A27: 44445 | B27: 751.4 | D27: =(B27-B26)/B26 -> -0.0043725984 | F27: 44445 | G27: 17369.25 | H27: =(G27-G26)/G26 -> 0.0026351336 | O27: Source
A28: 44452 | B28: 761 | D28: =(B28-B27)/B27 -> 0.012776151 | F28: 44452 | G28: 17585.15 | H28: =(G28-G27)/G27 -> 0.012430013 | O28: https://primeinvestor.in/nifty-50-returns/
A29: 44459 | B29: 758.85 | D29: =(B29-B28)/B28 -> -0.00282523 | F29: 44459 | G29: 17853.2 | H29: =(G29-G28)/G28 -> 0.015242975
A30: 44466 | B30: 781.35 | D30: =(B30-B29)/B29 -> 0.029650128 | F30: 44466 | G30: 17532.05 | H30: =(G30-G29)/G29 -> -0.017988372
A31: 44473 | B31: 784.2 | D31: =(B31-B30)/B30 -> 0.0036475331 | F31: 44473 | G31: 17895.2 | H31: =(G31-G30)/G30 -> 0.020713493
A32: 44480 | B32: 813.3 | D32: =(B32-B31)/B31 -> 0.037107881 | F32: 44480 | G32: 18338.55 | H32: =(G32-G31)/G31 -> 0.0247748
A33: 44487 | B33: 802.35 | D33: =(B33-B32)/B32 -> -0.013463667 | F33: 44487 | G33: 18114.9 | H33: =(G33-G32)/G32 -> -0.012195621
A34: 44494 | B34: 802.85 | D34: =(B34-B33)/B33 -> 0.00062316944 | F34: 44494 | G34: 17671.65 | H34: =(G34-G33)/G33 -> -0.024468807
A35: 44501 | B35: 805.05 | D35: =(B35-B34)/B34 -> 0.0027402379 | F35: 44501 | G35: 17916.8 | H35: =(G35-G34)/G34 -> 0.013872502
A36: 44508 | B36: 820.35 | D36: =(B36-B35)/B35 -> 0.019005031 | F36: 44508 | G36: 18102.75 | H36: =(G36-G35)/G35 -> 0.010378527
A37: 44515 | B37: 815.05 | D37: =(B37-B36)/B36 -> -0.006460657 | F37: 44515 | G37: 17764.8 | H37: =(G37-G36)/G36 -> -0.018668434
A38: 44522 | B38: 790.8 | D38: =(B38-B37)/B37 -> -0.029752776 | F38: 44522 | G38: 17026.45 | H38: =(G38-G37)/G37 -> -0.041562528
A39: 44529 | B39: 800.55 | D39: =(B39-B38)/B38 -> 0.012329287 | F39: 44529 | G39: 17196.7 | H39: =(G39-G38)/G38 -> 0.0099991484
A40: 44536 | B40: 823.05 | D40: =(B40-B39)/B39 -> 0.028105677 | F40: 44536 | G40: 17511.3 | H40: =(G40-G39)/G39 -> 0.018294208
... A195: 45621 | B195: 728.65 | D195: =(B195-B194)/B194 -> -0.0062056738 | F195: 45621 | G195: 24221.9 | H195: =(G195-G194)/G194 -> 0.01316128

Sheet CAPM (Daily) (Part-1)
A1: Data for Anupam Rasayan | D1: Returns | F1: DATA for NIFTY 50 | H1: Return | O1: Merket Returns for NIFTY 50 | S1: Average Return | T1: 91 day T-bill | U1: Cost of Equity
A2: Date | B2: Close | F2: Date | G2: Close | J2: Covariance | K2: Variance | L2: Beta | O2: 2024 | T2: (Risk free Rate) | U2: (CAPM)
A3: 3/24/2021 | B3: 526.8 | F3: 3/24/2021 | G3: 14549.4 | J3: =_xlfn.COVARIANCE.P(D4:D47,H4:H47) -> 8.4944211e-05 | K3: =_xlfn.VAR.P(H4:H47) -> 0.00012664872 | L3: =J3/K3 -> 0.67070724 | O3: 2023 | P3: 19.42 | S3: 15.609167 | T3: 6.5 | U3: =U4*100 -> 12.609584
A4: 3/25/2021 | B4: 494.75 | D4: =(B4-B3)/B3 -> -0.060839028 | F4: 3/25/2021 | G4: 14324.9 | H4: =(G4-G3)/G3 -> -0.01543019 | O4: 2022 | P4: 4.32 | S4: =S3/100 -> 0.15609167 | T4: =T3/100 -> 0.065 | U4: =T4+L3*(S4-T4) -> 0.12609584
A5: 3/26/2021 | B5: 495.7 | D5: =(B5-B4)/B4 -> 0.0019201617 | F5: 3/26/2021 | G5: 14507.3 | H5: =(G5-G4)/G4 -> 0.012733073 | O5: 2021 | P5: 24.12
A6: 3/30/2021 | B6: 480.3 | D6: =(B6-B5)/B5 -> -0.031067178 | F6: 3/30/2021 | G6: 14845.1 | H6: =(G6-G5)/G5 -> 0.023284829 | O6: 2020 | P6: 14.9
A7: 3/31/2021 | B7: 489.15 | D7: =(B7-B6)/B6 -> 0.018425984 | F7: 3/31/2021 | G7: 14690.7 | H7: =(G7-G6)/G6 -> -0.010400738 | O7: 2019 | P7: 12.02
A8: 44200 | B8: 516.95 | D8: =(B8-B7)/B7 -> 0.056833282 | F8: 44200 | G8: 14867.35 | H8: =(G8-G7)/G7 -> 0.012024614 | O8: 2018 | P8: 3.15
A9: 44320 | B9: 540.95 | D9: =(B9-B8)/B8 -> 0.046426153 | F9: 44320 | G9: 14637.8 | H9: =(G9-G8)/G8 -> -0.015439873 | O9: 2017 | P9: 28.65
A10: 44351 | B10: 552.1 | D10: =(B10-B9)/B9 -> 0.020611886 | F10: 44351 | G10: 14683.5 | H10: =(G10-G9)/G9 -> 0.0031220539 | O10: 2016 | P10: 3.01
A11: 44381 | B11: 557.4 | D11: =(B11-B10)/B10 -> 0.0095997102 | F11: 44381 | G11: 14819.05 | H11: =(G11-G10)/G10 -> 0.0092314503 | O11: 2015 | P11: -4.06
A12: 44412 | B12: 552.65 | D12: =(B12-B11)/B11 -> -0.0085217079 | F12: 44412 | G12: 14873.8 | H12: =(G12-G11)/G11 -> 0.0036945688 | O12: 2014 | P12: 31.39
A13: 44443 | B13: 555.25 | D13: =(B13-B12)/B12 -> 0.0047046051 | F13: 44443 | G13: 14834.85 | H13: =(G13-G12)/G12 -> -0.0026186987 | O13: 2013 | P13: 6.76
A14: 44534 | B14: 553.65 | D14: =(B14-B13)/B13 -> -0.0028815849 | F14: 44534 | G14: 14310.8 | H14: =(G14-G13)/G13 -> -0.035325602 | O14: 2012 | P14: 27.7
A15: 4/13/2021 | B15: 580.4 | D15: =(B15-B14)/B14 -> 0.048315723 | F15: 4/13/2021 | G15: 14504.8 | H15: =(G15-G14)/G14 -> 0.013556195 | O15: 2011 | P15: -24.62
A16: 4/15/2021 | B16: 594.7 | D16: =(B16-B15)/B15 -> 0.024638181 | F16: 4/15/2021 | G16: 14581.45 | H16: =(G16-G15)/G15 -> 0.0052844576 | O16: 2010 | P16: 17.95
A17: 4/16/2021 | B17: 579.95 | D17: =(B17-B16)/B16 -> -0.024802421 | F17: 4/16/2021 | G17: 14617.85 | H17: =(G17-G16)/G16 -> 0.0024963224 | O17: 2009 | P17: 75.76
A18: 4/19/2021 | B18: 552.05 | D18: =(B18-B17)/B17 -> -0.048107595 | F18: 4/19/2021 | G18: 14359.45 | H18: =(G18-G17)/G17 -> -0.017677018 | O18: 2008 | P18: -51.79
A19: 4/20/2021 | B19: 556.55 | D19: =(B19-B18)/B18 -> 0.0081514356 | F19: 4/20/2021 | G19: 14296.4 | H19: =(G19-G18)/G18 -> -0.0043908367 | O19: 2007 | P19: 54.77
A20: 4/22/2021 | B20: 554.4 | D20: =(B20-B19)/B19 -> -0.0038630851 | F20: 4/22/2021 | G20: 14406.15 | H20: =(G20-G19)/G19 -> 0.0076767578 | O20: 2006 | P20: 39.83
A21: 4/23/2021 | B21: 590 | D21: =(B21-B20)/B20 -> 0.064213564 | F21: 4/23/2021 | G21: 14341.35 | H21: =(G21-G20)/G20 -> -0.0044980789 | O21: 2005 | P21: 36.34
A22: 4/26/2021 | B22: 602.55 | D22: =(B22-B21)/B21 -> 0.021271186 | F22: 4/26/2021 | G22: 14485 | H22: =(G22-G21)/G21 -> 0.010016491 | O22: 2004 | P22: 10.68
A23: 4/27/2021 | B23: 629.6 | D23: =(B23-B22)/B22 -> 0.04489254 | F23: 4/27/2021 | G23: 14653.05 | H23: =(G23-G22)/G22 -> 0.011601657 | O23: 2003 | P23: 71.9
A24: 4/28/2021 | B24: 640 | D24: =(B24-B23)/B23 -> 0.016518424 | F24: 4/28/2021 | G24: 14864.55 | H24: =(G24-G23)/G23 -> 0.014433855 | O24: 2002 | P24: 3.25
A25: 4/29/2021 | B25: 632.2 | D25: =(B25-B24)/B24 -> -0.0121875 | F25: 4/29/2021 | G25: 14894.9 | H25: =(G25-G24)/G24 -> 0.0020417705 | O25: 2001 | P25: -16.18
A26: 4/30/2021 | B26: 624.25 | D26: =(B26-B25)/B25 -> -0.012575134 | F26: 4/30/2021 | G26: 14631.1 | H26: =(G26-G25)/G25 -> -0.01771076 | O26: 2000 | P26: -14.65
A27: 44260 | B27: 629.55 | D27: =(B27-B26)/B26 -> 0.0084901882 | F27: 44260 | G27: 14634.15 | H27: =(G27-G26)/G26 -> 0.00020846006 | O27: Source
A28: 44291 | B28: 636.55 | D28: =(B28-B27)/B27 -> 0.011119053 | F28: 44291 | G28: 14496.5 | H28: =(G28-G27)/G27 -> -0.009406081 | O28: https://primeinvestor.in/nifty-50-returns/
A29: 44321 | B29: 682.85 | D29: =(B29-B28)/B28 -> 0.072735842 | F29: 44321 | G29: 14617.85 | H29: =(G29-G28)/G28 -> 0.0083709861
A30: 44352 | B30: 703.9 | D30: =(B30-B29)/B29 -> 0.030826682 | F30: 44352 | G30: 14724.8 | H30: =(G30-G29)/G29 -> 0.0073163974
A31: 44382 | B31: 721.1 | D31: =(B31-B30)/B30 -> 0.024435289 | F31: 44382 | G31: 14823.15 | H31: =(G31-G30)/G30 -> 0.0066792079
A32: 44474 | B32: 736.15 | D32: =(B32-B31)/B31 -> 0.020870892 | F32: 44474 | G32: 14942.35 | H32: =(G32-G31)/G31 -> 0.0080414757
A33: 44505 | B33: 729.9 | D33: =(B33-B32)/B32 -> -0.0084901175 | F33: 44505 | G33: 14850.75 | H33: =(G33-G32)/G32 -> -0.0061302272
A34: 44535 | B34: 728.5 | D34: =(B34-B33)/B33 -> -0.001918071 | F34: 44535 | G34: 14696.5 | H34: =(G34-G33)/G33 -> -0.010386681
A35: 5/14/2021 | B35: 734.45 | D35: =(B35-B34)/B34 -> 0.0081674674 | F35: 5/14/2021 | G35: 14677.8 | H35: =(G35-G34)/G34 -> -0.0012724118
A36: 5/17/2021 | B36: 755.85 | D36: =(B36-B35)/B35 -> 0.02913745 | F36: 5/17/2021 | G36: 14923.15 | H36: =(G36-G35)/G35 -> 0.01671572
A37: 5/18/2021 | B37: 767.75 | D37: =(B37-B36)/B36 -> 0.015743865 | F37: 5/18/2021 | G37: 15108.1 | H37: =(G37-G36)/G36 -> 0.012393496
A38: 5/19/2021 | B38: 771.5 | D38: =(B38-B37)/B37 -> 0.0048844025 | F38: 5/19/2021 | G38: 15030.15 | H38: =(G38-G37)/G37 -> -0.005159484
A39: 5/20/2021 | B39: 771.55 | D39: =(B39-B38)/B38 -> 6.4808814e-05 | F39: 5/20/2021 | G39: 14906.05 | H39: =(G39-G38)/G38 -> -0.0082567373
A40: 5/21/2021 | B40: 769.4 | D40: =(B40-B39)/B39 -> -0.0027865984 | F40: 5/21/2021 | G40: 15175.3 | H40: =(G40-G39)/G39 -> 0.018063135
A41: 5/24/2021 | B41: 768.3 | D41: =(B41-B40)/B40 -> -0.0014296855 | F41: 5/24/2021 | G41: 15197.7 | H41: =(G41-G40)/G40 -> 0.0014760828
A42: 5/25/2021 | B42: 762.05 | D42: =(B42-B41)/B41 -> -0.0081348432 | F42: 5/25/2021 | G42: 15208.45 | H42: =(G42-G41)/G41 -> 0.00070734387
A43: 5/26/2021 | B43: 772.4 | D43: =(B43-B42)/B42 -> 0.013581786 | F43: 5/26/2021 | G43: 15301.45 | H43: =(G43-G42)/G42 -> 0.0061150216
A44: 5/27/2021 | B44: 767.35 | D44: =(B44-B43)/B43 -> -0.0065380632 | F44: 5/27/2021 | G44: 15337.85 | H44: =(G44-G43)/G43 -> 0.0023788595
A45: 5/28/2021 | B45: 761.5 | D45: =(B45-B44)/B44 -> -0.0076236398 | F45: 5/28/2021 | G45: 15435.65 | H45: =(G45-G44)/G44 -> 0.0063763826
A46: 5/31/2021 | B46: 754.25 | D46: =(B46-B45)/B45 -> -0.0095206829 | F46: 5/31/2021 | G46: 15582.8 | H46: =(G46-G45)/G45 -> 0.0095331262
A47: 44202 | B47: 726.9 | D47: =(B47-B46)/B46 -> -0.036261187 | F47: 44202 | G47: 15574.85 | H47: =(G47-G46)/G46 -> -0.00051017789
A48: 44233 | B48: 733.75 | D48: =(B48-B47)/B47 -> 0.0094235796 | F48: 44233 | G48: 15576.2 | H48: =(G48-G47)/G47 -> 8.6678202e-05
A49: 44261 | B49: 774.95 | D49: =(B49-B48)/B48 -> 0.056149915 | F49: 44261 | G49: 15690.35 | H49: =(G49-G48)/G48 -> 0.0073284883
A50: 44292 | B50: 769.25 | D50: =(B50-B49)/B49 -> -0.0073553132 | F50: 44292 | G50: 15670.25 | H50: =(G50-G49)/G49 -> -0.0012810422
A51: 44383 | B51: 772.9 | D51: =(B51-B50)/B50 -> 0.0047448814 | F51: 44383 | G51: 15751.65 | H51: =(G51-G50)/G50 -> 0.0051945566
A52: 44414 | B52: 760.9 | D52: =(B52-B51)/B51 -> -0.015525941 | F52: 44414 | G52: 15740.1 | H52: =(G52-G51)/G51 -> -0.00073325652
A53: 44445 | B53: 749.65 | D53: =(B53-B52)/B52 -> -0.014785123 | F53: 44445 | G53: 15635.35 | H53: =(G53-G52)/G52 -> -0.0066549768
A54: 44475 | B54: 768.7 | D54: =(B54-B53)/B53 -> 0.025411859 | F54: 44475 | G54: 15737.75 | H54: =(G54-G53)/G53 -> 0.0065492618
A55: 44506 | B55: 777.65 | D55: =(B55-B54)/B54 -> 0.011643034 | F55: 44506 | G55: 15799.35 | H55: =(G55-G54)/G54 -> 0.0039141555
A56: 6/14/2021 | B56: 757.3 | D56: =(B56-B55)/B55 -> -0.026168585 | F56: 6/14/2021 | G56: 15811.85 | H56: =(G56-G55)/G55 -> 0.00079117179
A57: 6/15/2021 | B57: 761.35 | D57: =(B57-B56)/B56 -> 0.0053479467 | F57: 6/15/2021 | G57: 15869.25 | H57: =(G57-G56)/G56 -> 0.0036301888
A58: 6/16/2021 | B58: 753 | D58: =(B58-B57)/B57 -> -0.010967361 | F58: 6/16/2021 | G58: 15767.55 | H58: =(G58-G57)/G57 -> -0.0064086204
A59: 6/17/2021 | B59: 741.1 | D59: =(B59-B58)/B58 -> -0.015803453 | F59: 6/17/2021 | G59: 15691.4 | H59: =(G59-G58)/G58 -> -0.0048295391
A60: 6/18/2021 | B60: 733.2 | D60: =(B60-B59)/B59 -> -0.01065983 | F60: 6/18/2021 | G60: 15683.35 | H60: =(G60-G59)/G59 -> -0.00051301987
A61: 6/21/2021 | B61: 724.2 | D61: =(B61-B60)/B60 -> -0.012274959 | F61: 6/21/2021 | G61: 15746.5 | H61: =(G61-G60)/G60 -> 0.0040265632
A62: 6/22/2021 | B62: 732.95 | D62: =(B62-B61)/B61 -> 0.012082298 | F62: 6/22/2021 | G62: 15772.75 | H62: =(G62-G61)/G61 -> 0.0016670371
A63: 6/23/2021 | B63: 743.95 | D63: =(B63-B62)/B62 -> 0.015007845 | F63: 6/23/2021 | G63: 15686.95 | H63: =(G63-G62)/G62 -> -0.0054397616
A64: 6/24/2021 | B64: 744.35 | D64: =(B64-B63)/B63 -> 0.00053767054 | F64: 6/24/2021 | G64: 15790.45 | H64: =(G64-G63)/G63 -> 0.0065978409
A65: 6/25/2021 | B65: 745.25 | D65: =(B65-B64)/B64 -> 0.0012091086 | F65: 6/25/2021 | G65: 15860.35 | H65: =(G65-G64)/G64 -> 0.0044267263
A66: 6/28/2021 | B66: 744 | D66: =(B66-B65)/B65 -> -0.0016772895 | F66: 6/28/2021 | G66: 15814.7 | H66: =(G66-G65)/G65 -> -0.0028782467
A67: 6/29/2021 | B67: 754.65 | D67: =(B67-B66)/B66 -> 0.014314516 | F67: 6/29/2021 | G67: 15748.45 | H67: =(G67-G66)/G66 -> -0.0041891405
A68: 6/30/2021 | B68: 760 | D68: =(B68-B67)/B67 -> 0.0070893792 | F68: 6/30/2021 | G68: 15721.5 | H68: =(G68-G67)/G67 -> -0.0017112795
A69: 44203 | B69: 754.7 | D69: =(B69-B68)/B68 -> -0.0069736842 | F69: 44203 | G69: 15680 | H69: =(G69-G68)/G68 -> -0.0026396972
A70: 44234 | B70: 757.95 | D70: =(B70-B69)/B69 -> 0.0043063469 | F70: 44234 | G70: 15722.2 | H70: =(G70-G69)/G69 -> 0.0026913265
A71: 44323 | B71: 764.7 | D71: =(B71-B70)/B70 -> 0.0089056006 | F71: 44323 | G71: 15834.35 | H71: =(G71-G70)/G70 -> 0.0071332256
A72: 44354 | B72: 763.8 | D72: =(B72-B71)/B71 -> -0.0011769321 | F72: 44354 | G72: 15818.25 | H72: =(G72-G71)/G71 -> -0.0010167768
A73: 44384 | B73: 768.9 | D73: =(B73-B72)/B72 -> 0.0066771406 | F73: 44384 | G73: 15879.65 | H73: =(G73-G72)/G72 -> 0.0038815925
A74: 44415 | B74: 783.1 | D74: =(B74-B73)/B73 -> 0.018467941 | F74: 44415 | G74: 15727.9 | H74: =(G74-G73)/G73 -> -0.009556256
A75: 44446 | B75: 812.45 | D75: =(B75-B74)/B74 -> 0.037479249 | F75: 44446 | G75: 15689.8 | H75: =(G75-G74)/G74 -> -0.0024224467
A76: 44537 | B76: 829.6 | D76: =(B76-B75)/B75 -> 0.021108991 | F76: 44537 | G76: 15692.6 | H76: =(G76-G75)/G75 -> 0.00017845989
A77: 7/13/2021 | B77: 825.35 | D77: =(B77-B76)/B76 -> -0.0051229508 | F77: 7/13/2021 | G77: 15812.35 | H77: =(G77-G76)/G76 -> 0.0076309853
A78: 7/14/2021 | B78: 816.95 | D78: =(B78-B77)/B77 -> -0.0101775 | F78: 7/14/2021 | G78: 15853.95 | H78: =(G78-G77)/G77 -> 0.002630855
A79: 7/15/2021 | B79: 815.05 | D79: =(B79-B78)/B78 -> -0.0023257237 | F79: 7/15/2021 | G79: 15924.2 | H79: =(G79-G78)/G78 -> 0.0044310724
A80: 7/16/2021 | B80: 814.35 | D80: =(B80-B79)/B79 -> -0.00085884302 | F80: 7/16/2021 | G80: 15923.4 | H80: =(G80-G79)/G79 -> -5.0238003e-05
A81: 7/19/2021 | B81: 799.45 | D81: =(B81-B80)/B80 -> -0.018296801 | F81: 7/19/2021 | G81: 15752.4 | H81: =(G81-G80)/G80 -> -0.010738913
A82: 7/20/2021 | B82: 781.2 | D82: =(B82-B81)/B81 -> -0.022828194 | F82: 7/20/2021 | G82: 15632.1 | H82: =(G82-G81)/G81 -> -0.0076369315
A83: 7/22/2021 | B83: 778.65 | D83: =(B83-B82)/B82 -> -0.0032642089 | F83: 7/22/2021 | G83: 15824.05 | H83: =(G83-G82)/G82 -> 0.01227922
A84: 7/23/2021 | B84: 766.3 | D84: =(B84-B83)/B83 -> -0.015860785 | F84: 7/23/2021 | G84: 15856.05 | H84: =(G84-G83)/G83 -> 0.0020222383
A85: 7/26/2021 | B85: 752.3 | D85: =(B85-B84)/B84 -> -0.018269607 | F85: 7/26/2021 | G85: 15824.45 | H85: =(G85-G84)/G84 -> -0.0019929301
A86: 7/27/2021 | B86: 730.85 | D86: =(B86-B85)/B85 -> -0.028512561 | F86: 7/27/2021 | G86: 15746.45 | H86: =(G86-G85)/G85 -> -0.0049290813
A87: 7/28/2021 | B87: 717.7 | D87: =(B87-B86)/B86 -> -0.017992748 | F87: 7/28/2021 | G87: 15709.4 | H87: =(G87-G86)/G86 -> -0.0023529113
A88: 7/29/2021 | B88: 728.6 | D88: =(B88-B87)/B87 -> 0.015187404 | F88: 7/29/2021 | G88: 15778.45 | H88: =(G88-G87)/G87 -> 0.0043954575
A89: 7/30/2021 | B89: 726.4 | D89: =(B89-B88)/B88 -> -0.0030194894 | F89: 7/30/2021 | G89: 15763.05 | H89: =(G89-G88)/G88 -> -0.00097601475
A90: 44235 | B90: 723.45 | D90: =(B90-B89)/B89 -> -0.0040611233 | F90: 44235 | G90: 15885.15 | H90: =(G90-G89)/G89 -> 0.0077459629
A91: 44263 | B91: 720.4 | D91: =(B91-B90)/B90 -> -0.0042159099 | F91: 44263 | G91: 16130.75 | H91: =(G91-G90)/G90 -> 0.015460981
A92: 44294 | B92: 712.75 | D92: =(B92-B91)/B91 -> -0.0106191 | F92: 44294 | G92: 16258.8 | H92: =(G92-G91)/G91 -> 0.0079382546
A93: 44324 | B93: 711.85 | D93: =(B93-B92)/B92 -> -0.0012627148 | F93: 44324 | G93: 16294.6 | H93: =(G93-G92)/G92 -> 0.0022018845
A94: 44355 | B94: 712.4 | D94: =(B94-B93)/B93 -> 0.00077263468 | F94: 44355 | G94: 16238.2 | H94: =(G94-G93)/G93 -> -0.0034612694
A95: 44447 | B95: 709.6 | D95: =(B95-B94)/B94 -> -0.0039303762 | F95: 44447 | G95: 16258.25 | H95: =(G95-G94)/G94 -> 0.0012347428
A96: 44477 | B96: 706.55 | D96: =(B96-B95)/B95 -> -0.0042981962 | F96: 44477 | G96: 16280.1 | H96: =(G96-G95)/G95 -> 0.0013439331
A97: 44508 | B97: 715.95 | D97: =(B97-B96)/B96 -> 0.013304083 | F97: 44508 | G97: 16282.25 | H97: =(G97-G96)/G96 -> 0.00013206307
A98: 44538 | B98: 736.3 | D98: =(B98-B97)/B97 -> 0.028423773 | F98: 44538 | G98: 16364.4 | H98: =(G98-G97)/G97 -> 0.0050453715
A99: 8/13/2021 | B99: 754.15 | D99: =(B99-B98)/B98 -> 0.024242836 | F99: 8/13/2021 | G99: 16529.1 | H99: =(G99-G98)/G98 -> 0.01006453
A100: 8/16/2021 | B100: 760.8 | D100: =(B100-B99)/B99 -> 0.0088178744 | F100: 8/16/2021 | G100: 16563.05 | H100: =(G100-G99)/G99 -> 0.0020539533
...

Sheet Part-2 (Balance Sheet)
D1: Financial Year | N1: Capital Structure and Debt Analysis
C2: 2018 | D2: 2019 | E2: 2020 | F2: 2021 | G2: 2022 | H2: 2023 | I2: 2024
Q3: FY | R3: 2019 | S3: 2020 | T3: 2021 | U3: 2022 | V3: 2023 | W3: 2024
A4: Balance Sheet | C4: Shares outstanding numbers in cr. Other numbers in ₹ cr | O4: Proportion of Debt vs. Equity
A5: Statements | P5: Debt Ratio | R5: =D36/D22 -> 0.61655198 | S5: =E36/E22 -> 0.6433653 | T5: =F36/F22 -> 0.31531767 | U5: =G36/G22 -> 0.40258981 | V5: =H36/H22 -> 0.33612411 | W5: =I36/I22 -> 0.36313121
A6: Current Assests | D6: 423.46 | E6: 551.75 | F6: 1090.47 | G6: 1446.64 | H6: 2111.2 | I6: 2226.62 | P6: Equity Ratio | R6: =D38/D22 -> 0.38344802 | S6: =E38/E22 -> 0.3566347 | T6: =F38/F22 -> 0.68468233 | U6: =G38/G22 -> 0.59741019 | V6: =H38/H22 -> 0.66387589 | W6: =I38/I22 -> 0.63686879
P7: Current Ratio | R7: =D6/D24 -> 1.2476356 | S7: =E6/E24 -> 1.1169254 | T7: =F6/F24 -> 2.5926534 | U7: =G6/G24 -> 2.4310826 | V7: =H6/H24 -> 2.6038481 | W7: =I6/I24 -> 1.6929639
B8: Cash and Short term investments | D8: 7.06 | E8: 26.83 | F8: 295.71 | G8: 209.71 | H8: 629.92 | I8: 354.43
B9: Total Recivables | D9: 120.59 | E9: 129.49 | F9: 205.49 | G9: 280.1 | H9: 415.08 | I9: 579.39
B10: Total Inventory | D10: 195.37 | E10: 297.04 | F10: 492.22 | G10: 863.19 | H10: 931.47 | I10: 1055.32
B11: Other Current Assets | D11: 100.44 | E11: 98.39 | F11: 97.05 | G11: 93.64 | H11: 134.73 | I11: 237.48
A12: +
A13: Non Current Assets | D13: 899.04 | E13: 1112.53 | F13: 1207.53 | G13: 1443.92 | H13: 1666.72 | I13: 2375.05
B15: Loans & Advances | D15: 0 | E15: 0 | F15: 0 | G15: 0 | H15: 0 | I15: 0
B16: Net Property/Plant/Equipment | D16: 871.51 | E16: 1078.29 | F16: 1158.28 | G16: 1245.94 | H16: 1414.37 | I16: 1987.55
B17: Goodwill & Intangibles | D17: 0 | E17: 0 | F17: 0 | G17: 0 | H17: 123.21 | I17: 123.21
B18: Long Term Investments | D18: 0.4 | E18: 0.4 | F18: 0.02 | G18: 148.82 | H18: 1.42 | I18: 1.45
B19: Deferred Tax Assets (Net) | D19: 0 | E19: 0 | F19: 0 | G19: 0 | H19: 0 | I19: 0
B20: Other Assets | D20: 27.13 | E20: 33.84 | F20: 49.23 | G20: 49.16 | H20: 127.73 | I20: 262.85
A21: =
A22: Total Assets | D22: 1322.5 | E22: 1664.28 | F22: 2298 | G22: 2890.56 | H22: 3777.92 | I22: 4601.67
A24: Current Liability | D24: 339.41 | E24: 493.99 | F24: 420.6 | G24: 595.06 | H24: 810.8 | I24: 1315.22
B26: Accounts Payable | D26: 126.88 | E26: 183.02 | F26: 229.72 | G26: 246.63 | H26: 324.94 | I26: 437.13 | Q26: FY | R26: =R3 -> 2019 | S26: =S3 -> 2020 | T26: =T3 -> 2021 | U26: =U3 -> 2022 | V26: =V3 -> 2023 | W26: =W3 -> 2024
B27: Total Deposits | D27: 0 | E27: 0 | F27: 0 | G27: 0 | H27: 0 | I27: 0 | O27: Company’s Ability to Service its Debt
B28: Other Current Liabilities | D28: 212.53 | E28: 310.97 | F28: 190.88 | G28: 348.43 | H28: 485.86 | I28: 878.09 | P28: Interest Coverage Ratio | R28: =C81/C83 -> 2.4591479 | S28: =D81/D83 -> 3.6989733 | T28: =E81/E83 -> 2.5832965 | U28: =F81/F83 -> 2.4591479 | V28: =G81/G83 -> 8.1959131 | W28: =H81/H83 -> 5.91015
A29: +
A30: Non-Current Liabilities | D30: 475.98 | E30: 576.75 | F30: 304 | G30: 568.65 | H30: 459.05 | I30: 355.79
B32: Total Long Term Debt | D32: 462.31 | E32: 524.73 | F32: 279.63 | G32: 513.98 | H32: 381.92 | I32: 237.92
B33: Deferred Tax Liabilities (Net) | D33: 13.69 | E33: 19.08 | F33: 24.38 | G33: 54.65 | H33: 76.03 | I33: 116.39
B34: Other Liabilities | D34: -0.02 | E34: 32.94 | F34: -0.01 | G34: 0.02 | H34: 1.1 | I34: 1.48
A35: =
A36: Total Liabilities | D36: 815.39 | E36: 1070.74 | F36: 724.6 | G36: 1163.71 | H36: 1269.85 | I36: 1671.01
A38: Total Equity | D38: 507.11 | E38: 593.54 | F38: 1573.4 | G38: 1726.85 | H38: 2508.07 | I38: 2930.66
B40: Common Stock | D40: 74.63 | E40: 78.13 | F40: 99.92 | G40: 100.25 | H40: 107.47 | I40: 109.79
B41: Additional Paid-in Capital | D41: 210.88 | E41: 242.75 | F41: 1130.65 | G41: 1137.19 | H41: 1611.52 | I41: 1807.9
B42: Reserves & Surplus | D42: 221.6 | E42: 272.66 | F42: 342.83 | G42: 489.41 | H42: 653.6 | I42: 750.84
B43: Minority Interest | D43: 0 | E43: 0 | F43: 0 | G43: 0 | H43: 135.48 | I43: 169.63
B44: Other Equity | D44: 0 | E44: 0 | F44: 0 | G44: 0 | H44: 0 | I44: 92.5
A46: Total Liability and SE | D46: 1322.5 | E46: 1664.28 | F46: 2298 | G46: 2890.56 | H46: 3777.92 | I46: 4601.67 | O46: Dividend Policy
Q47: FY | R47: =R26 -> 2019 | S47: =S26 -> 2020 | T47: =T26 -> 2021 | U47: =U26 -> 2022 | V47: =V26 -> 2023 | W47: =W26 -> 2024
A48: Total Outstanding Shares | D48: 5 | E48: 5 | F48: 9.99 | G48: 10.02 | H48: 10.75 | I48: 10.98
P49: DPS | R49: =D92 -> 0 | S49: =E92 -> 0 | T49: =F92 -> 0.5 | U49: =G92 -> 1 | V49: =H92 -> 2.5 | W49: =I92 -> 1.25
P50: Payout Ratio | R50: =D93 -> 0 | S50: =E93 -> 0 | T50: =F93 -> 0.05 | U50: =G93 -> 0.07 | V50: =H93 -> 0.14 | W50: =I93 -> 0.11
A51: Cash Flow Statements | C51: All numbers in ₹ cr
A52: Statements
A54: Net Change in Cash | C54: -0.55 | D54: -5.56 | E54: 18.61 | F54: 224.15 | G54: -198.91 | H54: 140.06 | I54: 61.99
B56: Cash from Operating Activities | C56: -20.26 | D56: 38.92 | E56: 94.94 | F56: 1.46 | G56: -171.23 | H56: 292.07 | I56: 59.03
B57: Cash from Investing Activities | C57: -255.13 | D57: -250.22 | E57: -178.2 | F57: -193.08 | G57: -412.04 | H57: -522.66 | I57: -392.11
B58: Cash from Financing Activities | C58: 274.84 | D58: 205.74 | E58: 101.87 | F58: 415.77 | G58: 384.36 | H58: 370.65 | I58: 395.07
A60: Changes in Working Capital | C60: -102.24 | D60: -70.62 | E60: -57.66 | F60: -218.19 | G60: -477.33 | H60: -164.94 | I60: -329.32
A62: Capital Expenditure | C62: 255.61 | D62: 248.27 | E62: 180.39 | F62: 146.02 | G62: 146.86 | H62: 220.77 | I62: 715.99
A64: Free Cash Flow | C64: -275.87 | D64: -209.35 | E64: -85.45 | F64: -144.56 | G64: -318.09 | H64: 71.3 | I64: -656.96
A66: Income Statements | C66: EPS and DPS in ₹. Other numbers except Payout Ratio in ₹ cr | J66: TTM
A67: Statements
O68: OVERALL ANALYSIS
A69: Total Revenue | C69: 837.5 | D69: 520.96 | E69: 539.76 | F69: 837.5 | G69: 1081.76 | H69: 1611.95 | I69: 1505.32 | J69: 1267.12
J70: 939.33
A71: - | B71: Raw Materials | C71: 0 | D71: 263.48 | E71: 296.16 | F71: 469.36 | G71: 691.7 | H71: 767.59 | I71: 693.14 | J71: 0
A72: - | B72: Power & Fuel Cost | C72: 0 | D72: 0 | E72: 0 | F72: 0 | G72: 0 | H72: 0.77 | I72: 1.17 | J72: 0
A73: - | B73: Employee Cost | C73: 617.3 | D73: 18.59 | E73: 21.09 | F73: 32.44 | G73: 48.5 | H73: 68.9 | I73: 75.14 | J73: 0
A74: - | B74: Selling & Administrative Expenses | C74: 0 | D74: 26.92 | E74: 28.87 | F74: 37.11 | G74: 56.2 | H74: 80.58 | I74: 86.67 | J74: 0
A75: - | B75: Operating & Other expenses | C75: 0 | D75: 99.37 | E75: 48.01 | F75: 78.39 | G75: -27.44 | H75: 252.7 | I75: 238.29 | J75: 0
A76: =
A77: EBITDA | C77: 220.2 | D77: 112.6 | E77: 145.63 | F77: 220.2 | G77: 312.8 | H77: 441.41 | I77: 410.91 | J77: 327.79
A78: EBITDA MARGIN | C78: =C77/C69 -> 0.26292537 | D78: =D77/D69 -> 0.21613943 | E78: =E77/E69 -> 0.2698051 | F78: =F77/F69 -> 0.26292537 | G78: =G77/G69 -> 0.28915841 | H78: =H77/H69 -> 0.27383604 | I78: =I77/I69 -> 0.27297186 | J78: =J77/J69 -> 0.258689
A79: - | B79: Depreciation/Amortization | C79: 51.65 | D79: 22.53 | E79: 28.71 | F79: 51.65 | G79: 60.12 | H79: 71.08 | I79: 79.7 | J79: 83.51
A80: =
A81: PBIT | C81: 168.55 | D81: 90.07 | E81: 116.92 | F81: 168.55 | G81: 252.68 | H81: 370.33 | I81: 331.21 | J81: 244.28
A82: EBIT MARGIN | C82: =C81/C69 -> 0.20125373 | D82: =D81/D69 -> 0.17289235 | E82: =E81/E69 -> 0.21661479 | F82: =F81/F69 -> 0.20125373 | G82: =G81/G69 -> 0.23358231 | H82: =H81/H69 -> 0.22974038 | I82: =I81/I69 -> 0.22002631 | J82: =J81/J69 -> 0.19278364
A83: - | B83: Interest & Other Items | C83: 68.54 | D83: 24.35 | E83: 45.26 | F83: 68.54 | G83: 30.83 | H83: 62.66 | I83: 89.43 | J83: 100.24
A84: =
A85: PBT | C85: 100.01 | D85: 65.72 | E85: 71.66 | F85: 100.01 | G85: 221.85 | H85: 307.67 | I85: 241.78 | J85: 144.04
A87: - | B87: Taxes & Other Items | C87: 29.71 | D87: 16.47 | E87: 18.47 | F87: 29.71 | G87: 69.68 | H87: 126.82 | I87: 113.17 | J87: 74.15
A88: =
A89: Net Income | C89: 70.3 | D89: 49.25 | E89: 53.19 | F89: 70.3 | G89: 152.17 | H89: 180.85 | I89: 128.61 | J89: 69.89
A90: NET PROFIT MARGIN | C90: =C89/C69 -> 0.083940299 | D90: =D89/D69 -> 0.094537009 | E90: =E89/E69 -> 0.098543797 | F90: =F89/F69 -> 0.083940299 | G90: =G89/G69 -> 0.14066891 | H90: =H89/H69 -> 0.11219331 | I90: =I89/I69 -> 0.085436983 | J90: =J89/J69 -> 0.055156576
A91: EPS | C91: 8.56 | D91: 9.85 | E91: 10.64 | F91: 9.38 | G91: 15.2 | H91: 17.41 | I91: 11.84 | J91: 6.37
A92: DPS | C92: 0 | D92: 0 | E92: 0 | F92: 0.5 | G92: 1 | H92: 2.5 | I92: 1.25 | J92: 1.25
A93: Payout ratio | C93: 0 | D93: 0 | E93: 0 | F93: 0.05 | G93: 0.07 | H93: 0.14 | I93: 0.11 | J93: 0.2
A95: BALANCE SHEET, CASH FLOW STATEMENT, INCOME STATEMENT ENDS HERE

Sheet Part-3
A1: Parameters | B1: Ranking (1-5) | C1: Justification
A2: Financial Obligations | B2: 5 | C2: The company has a strong current ratio and interest coverage ratio, indicating good liquidity and solvency.
A3: Returns to Shareholders | B3: 2 | C3: The firm's ROE is average compared to it's peers, and has a moderate dividend yield compared to its peers.
A4: Stock Price Stability | B4: 2 | C4: The stock has a higher volatility (1.267) than the market.
A5: Growth in Revenue and Earnings | B5: 5 | C5: The firm has shown consistent earnings and sales growth above industry average.
A6: Environmental and Social Initiatives | B6: 3 | C6: The firm has taken a keen interest in meeting regulatory compliances and improving the lives of the community and employee alike.
A9: Parameters (Justifications)
A10: 1.) Financial Obligations | C10: The company's interest coverage ratio, Equity ratio shows an upwards trend while Debt ratio shows a downward trend this shows that every year the firm's equity is increasing faster than it's debt imporving its financial position and improving its ability to service it's debt. | E10: ='Part-2 (Balance Sheet)'!Q3 -> FY | F10: ='Part-2 (Balance Sheet)'!R3 -> 2019 | G10: ='Part-2 (Balance Sheet)'!S3 -> 2020 | H10: ='Part-2 (Balance Sheet)'!T3 -> 2021 | I10: ='Part-2 (Balance Sheet)'!U3 -> 2022 | J10: ='Part-2 (Balance Sheet)'!V3 -> 2023 | K10: ='Part-2 (Balance Sheet)'!W3 -> 2024
D11: ='Part-2 (Balance Sheet)'!P5 -> Debt Ratio | F11: ='Part-2 (Balance Sheet)'!R5 -> 0.61655198 | G11: ='Part-2 (Balance Sheet)'!S5 -> 0.6433653 | H11: ='Part-2 (Balance Sheet)'!T5 -> 0.31531767 | I11: ='Part-2 (Balance Sheet)'!U5 -> 0.40258981 | J11: ='Part-2 (Balance Sheet)'!V5 -> 0.33612411 | K11: ='Part-2 (Balance Sheet)'!W5 -> 0.36313121
D12: ='Part-2 (Balance Sheet)'!P6 -> Equity Ratio | F12: ='Part-2 (Balance Sheet)'!R6 -> 0.38344802 | G12: ='Part-2 (Balance Sheet)'!S6 -> 0.3566347 | H12: ='Part-2 (Balance Sheet)'!T6 -> 0.68468233 | I12: ='Part-2 (Balance Sheet)'!U6 -> 0.59741019 | J12: ='Part-2 (Balance Sheet)'!V6 -> 0.66387589 | K12: ='Part-2 (Balance Sheet)'!W6 -> 0.63686879
D13: ='Part-2 (Balance Sheet)'!P7 -> Current Ratio | F13: ='Part-2 (Balance Sheet)'!R7 -> 1.2476356 | G13: ='Part-2 (Balance Sheet)'!S7 -> 1.1169254 | H13: ='Part-2 (Balance Sheet)'!T7 -> 2.5926534 | I13: ='Part-2 (Balance Sheet)'!U7 -> 2.4310826 | J13: ='Part-2 (Balance Sheet)'!V7 -> 2.6038481 | K13: ='Part-2 (Balance Sheet)'!W7 -> 1.6929639
D14: ='Part-2 (Balance Sheet)'!P28 -> Interest Coverage Ratio | F14: ='Part-2 (Balance Sheet)'!R28 -> 2.4591479 | G14: ='Part-2 (Balance Sheet)'!S28 -> 3.6989733 | H14: ='Part-2 (Balance Sheet)'!T28 -> 2.5832965 | I14: ='Part-2 (Balance Sheet)'!U28 -> 2.4591479 | J14: ='Part-2 (Balance Sheet)'!V28 -> 8.1959131 | K14: ='Part-2 (Balance Sheet)'!W28 -> 5.91015
A33: 2.) Returns to Shareholders
C34: The firm's dividend yield (0.17) is much less than most of it's peer in speciality chemical sector and so is it's ROE of 5. | E34: Ratio | G34: P/E | H34: ROE | I34: ROCE | J34: Dividend Yield | K34: Sales Growth (5 years) | L34: EBIDT Growth 5 years | M34: Profit Growth 5 years | N34: EPS (3 years) | O34: EPS(5 years)
D35: Competitors
D37: Gujarat Fluorochemicals Ltd | G37: 102 | H37: 7.69 | I37: 9.76 | J37: 0.08 | K37: 9.42 | L37: 3.31 | M37: -18.8 | N37: 59.1 | O37: -
D38: Vinati Organics Ltd | G38: 51.1 | H38: 13.8 | I38: 18.5 | J38: 0.38 | K38: 11 | L38: 2.31 | M38: 2.72 | N38: 5.98 | O38: 2.55
D39: Akzo Nobel India Ltd | G39: 38.1 | H39: 32.3 | I39: 42.3 | J39: 2.06 | K39: 6.3 | L39: 13.3 | M39: 17.2 | N39: 26.8 | O39: 17.2
D40: Navin Fluorine International Ltd | G40: 76.2 | H40: 10.1 | I40: 10.4 | J40: 0.36 | K40: 15.7 | L40: 12.5 | M40: 9.35 | N40: -2.24 | O40: 9.3
D41: Fine Organic Industries Ltd | G41: 40.8 | H41: 21.7 | I41: 29 | J41: 0.19 | K41: 13.3 | L41: 17.9 | M41: 23.3 | N41: 47.4 | O41: 23.3
D42: Aarti Industries Ltd | G42: 35.3 | H42: 8.22 | I42: 7.47 | J42: 0.23 | K42: 8.86 | L42: 0.48 | M42: -3.07 | N42: -8.3 | O42: -3.92
D43: Supreme Petrochem Ltd | G43: 31.6 | H43: 16.8 | I43: 22.5 | J43: 1.3 | K43: 10.5 | L43: 37.6 | M43: 45.9 | N43: -12 | O43: 46.7
F45: Average | G45: =AVERAGE(G37:G43) -> 53.585714 | H45: =AVERAGE(H37:H43) -> 15.801429 | I45: =AVERAGE(I37:I43) -> 19.99 | J45: =AVERAGE(J37:J43) -> 0.65714286 | K45: =AVERAGE(K37:K43) -> 10.725714 | L45: =AVERAGE(L37:L43) -> 12.485714 | M45: =AVERAGE(M37:M43) -> 10.942857 | N45: =AVERAGE(N37:N43) -> 16.677143 | O45: =AVERAGE(O37:O43) -> 15.855
D47: Anupam Rasayan | G47: 115 | H47: 5 | I47: 9 | J47: 0.17 | K47: 24.1 | L47: 29.2 | M47: 20.6 | N47: 17.6 | O47: 3.08
A49: 3.) Stock Price Stability
C50: The stock's beta is 1.2675 which means the stock is about 26% more volatile than the broader market.
A52: 4.) Growth in Revenue and Earnings | C52: The stock has show high profit (20.6%) and sales growth (24.1%) better than most of its peers.
A54: 5.) Environmental and Social Initiatives
C55: 1. Regulatory Compliance and Risk Mitigation By adopting sustainable practices like zero liquid discharge (ZLD), renewable energy use, and proper waste management, the company ensures compliance with environmental regulations. Avoiding penalties or legal issues fosters operational continuity and strengthens its reputation with regulators and stakeholders. 2. Cost Efficiency Through Sustainable Practices Investments in renewable energy (e.g., solar power) and water recycling reduce long-term operating costs. Efficient resource utilization minimizes waste, turning potential liabilities into value-adding processes. 3. Enhanced Brand Reputation Commitment to sustainability and social responsibility attracts investors, customers, and partners who prioritize ethical and eco-friendly practices. A strong ESG (Environmental, Social, and Governance) profile can lead to inclusion in sustainability indexes, further improving investor confidence. 4. Customer and Market Advantage Many global customers, particularly in the specialty chemicals industry, prefer suppliers with strong environmental credentials. Compliance with international sustainability standards enhances export opportunities and helps attract clients who are aligning with ESG goals. 5. Employee Retention and Productivity Initiatives like workplace safety programs, skill development, and community engagement improve employee satisfaction and loyalty. A motivated and skilled workforce contributes to long-term operational excellence. 6. Future-Proofing Against Market Trends Global industries are increasingly moving toward green chemistry and sustainable products. Anupam Rasayan's focus on sustainability positions it well to adapt to market changes and regulations. Its commitment to eco-friendly manufacturing gives it a competitive edge as customers and governments demand greener solutions.
